Metadata-Version: 2.4
Name: whitespacetokenizer
Version: 1.0.4
Summary: Fast python whitespace tokenizer wtitten in cython.
Home-page: https://github.com/mdocekal/whitespacetokenizer
Author: Martin Dočekal
License: The Unlicense
Keywords: tokenizer,whitespace
Requires-Python: >=3.10
License-File: LICENSE
Requires-Dist: setuptools
Requires-Dist: cython
Dynamic: author
Dynamic: description
Dynamic: description-content-type
Dynamic: home-page
Dynamic: keywords
Dynamic: license
Dynamic: license-file
Dynamic: requires-dist
Dynamic: requires-python
Dynamic: summary
